{"version":"10.2.2","10.2.2":{"packages":{"next":{"name":"next","version":"10.2.2","tarball":"https://registry.npmjs.org/next/-/next-10.2.2.tgz","sha1":"aadcc526e420282b4a735b0595041195d748a91d","dependencies":["@babel/runtime","@hapi/accept","@next/env","@next/polyfill-module","@next/react-dev-overlay","@next/react-refresh-utils","@opentelemetry/api","assert","ast-types","browserify-zlib","browserslist","buffer","caniuse-lite","chalk","chokidar","constants-browserify","crypto-browserify","cssnano-simple","domain-browser","encoding","etag","find-cache-dir","get-orientation","https-browserify","jest-worker","native-url","node-fetch","node-html-parser","node-libs-browser","os-browserify","p-limit","path-browserify","pnp-webpack-plugin","postcss","process","prop-types","querystring-es3","raw-body","react-is","react-refresh","stream-browserify","stream-http","string_decoder","styled-jsx","timers-browserify","tty-browserify","use-subscription","util","vm-browserify","watchpack"]},"@babel/runtime":{"name":"@babel/runtime","version":"7.12.5","tarball":"https://registry.npmjs.org/@babel/runtime/-/runtime-7.12.5.tgz","sha1":"410e7e487441e1b360c29be715d870d9b985882e","dependencies":["regenerator-runtime"]},"regenerator-runtime":{"name":"regenerator-runtime","version":"0.13.4","tarball":"https://registry.npmjs.org/regenerator-runtime/-/regenerator-runtime-0.13.4.tgz","sha1":"e96bf612a3362d12bb69f7e8f74ffeab25c7ac91"},"@hapi/accept":{"name":"@hapi/accept","version":"5.0.2","tarball":"https://registry.npmjs.org/@hapi/accept/-/accept-5.0.2.tgz","sha1":"ab7043b037e68b722f93f376afb05e85c0699523","dependencies":["@hapi/boom","@hapi/hoek"]},"@hapi/boom":{"name":"@hapi/boom","version":"9.x.x"},"@next/env":{"name":"@next/env","version":"10.2.2","tarball":"https://registry.npmjs.org/@next/env/-/env-10.2.2.tgz","sha1":"cb61f6c29f349815108184c2f1926ada65458e28","dependencies":[]},"@next/polyfill-module":{"name":"@next/polyfill-module","version":"10.2.2","tarball":"https://registry.npmjs.org/@next/polyfill-module/-/polyfill-module-10.2.2.tgz","sha1":"48d108dd562ed021dd23510c0ffe96badf5f9c04","dependencies":[]},"@next/react-dev-overlay":{"name":"@next/react-dev-overlay","version":"10.2.2","tarball":"https://registry.npmjs.org/@next/react-dev-overlay/-/react-dev-overlay-10.2.2.tgz","sha1":"88fb5013d3df70bd37b854234c41d884e108a149","dependencies":["@babel/code-frame","anser","chalk","classnames","css.escape","data-uri-to-buffer","platform","shell-quote","source-map","stacktrace-parser","strip-ansi"]},"@babel/code-frame":{"name":"@babel/code-frame","version":"7.12.11","tarball":"https://registry.npmjs.org/@babel/code-frame/-/code-frame-7.12.11.tgz","sha1":"f4ad435aa263db935b8f10f2c552d23fb716a63f","dependencies":["@babel/highlight"]},"@babel/highlight":{"name":"@babel/highlight","version":"7.10.4","tarball":"https://registry.npmjs.org/@babel/highlight/-/highlight-7.10.4.tgz","sha1":"7d1bdfd65753538fabe6c38596cdb76d9ac60143","dependencies":["@babel/helper-validator-identifier","chalk","js-tokens"]},"@babel/helper-validator-identifier":{"name":"@babel/helper-validator-identifier","version":"7.10.4","tarball":"https://registry.npmjs.org/@babel/helper-validator-identifier/-/helper-validator-identifier-7.10.4.tgz","sha1":"a78c7a7251e01f616512d31b10adcf52ada5e0d2"},"anser":{"name":"anser","version":"1.4.9","tarball":"https://registry.npmjs.org/anser/-/anser-1.4.9.tgz","sha1":"1f85423a5dcf8da4631a341665ff675b96845760","dependencies":[]},"chalk":{"name":"chalk","version":"2.4.2","tarball":"https://registry.npmjs.org/chalk/-/chalk-2.4.2.tgz","sha1":"cd42541677a54333cf541a49108c1432b44c9424","dependencies":["ansi-styles","escape-string-regexp","supports-color"]},"ansi-styles":{"name":"ansi-styles","version":"3.2.1","tarball":"https://registry.npmjs.org/ansi-styles/-/ansi-styles-3.2.1.tgz","sha1":"41fbb20243e50b12be0f04b8dedbf07520ce841d","dependencies":["color-convert"]},"color-convert":{"name":"color-convert","version":"1.9.0","tarball":"https://registry.npmjs.org/color-convert/-/color-convert-1.9.0.tgz","sha1":"1accf97dd739b983bf994d56fec8f95853641b7a","dependencies":["color-name"]},"color-name":{"name":"color-name","version":"1.1.1","tarball":"https://registry.npmjs.org/color-name/-/color-name-1.1.1.tgz","sha1":"4b1415304cf50028ea81643643bd82ea05803689"},"supports-color":{"name":"supports-color","version":"8.0.0","tarball":"https://registry.npmjs.org/supports-color/-/supports-color-8.0.0.tgz","sha1":"51fc88b5f0b8c47a64fcc54941f41a0ff9e695e3","dependencies":["has-flag"]},"has-flag":{"name":"has-flag","version":"4.0.0","tarball":"https://registry.npmjs.org/has-flag/-/has-flag-4.0.0.tgz","sha1":"944771fd9c81c81265c4d6941860da06bb59479b"},"classnames":{"name":"classnames","version":"2.2.6","tarball":"https://registry.npmjs.org/classnames/-/classnames-2.2.6.tgz","sha1":"43935bffdd291f326dad0a205309b38d00f650ce"},"@next/react-refresh-utils":{"name":"@next/react-refresh-utils","version":"10.2.2","tarball":"https://registry.npmjs.org/@next/react-refresh-utils/-/react-refresh-utils-10.2.2.tgz","sha1":"69dd150e3656aebe63fc828916105f1472810488","dependencies":[]},"@opentelemetry/api":{"name":"@opentelemetry/api","version":"0.14.0","tarball":"https://registry.npmjs.org/@opentelemetry/api/-/api-0.14.0.tgz","sha1":"4e17d8d2f1da72b19374efa7b6526aa001267cae","dependencies":["@opentelemetry/context-base"]},"@opentelemetry/context-base":{"name":"@opentelemetry/context-base","version":"0.14.0","tarball":"https://registry.npmjs.org/@opentelemetry/context-base/-/context-base-0.14.0.tgz","sha1":"c67fc20a4d891447ca1a855d7d70fa79a3533001"},"assert":{"name":"assert","version":"1.1.1","tarball":"https://registry.npmjs.org/assert/-/assert-1.1.1.tgz","sha1":"766549ef4a6014b1e19c7c53f9816eabda440760","dependencies":["util"]},"es6-object-assign":{"name":"es6-object-assign","version":"1.1.0","tarball":"https://registry.npmjs.org/es6-object-assign/-/es6-object-assign-1.1.0.tgz","sha1":"c2c3582656247c39ea107cb1e6652b6f9f24523c"},"ast-types":{"name":"ast-types","version":"0.13.2","tarball":"https://registry.npmjs.org/ast-types/-/ast-types-0.13.2.tgz","sha1":"df39b677a911a83f3a049644fb74fdded23cea48","dependencies":[]},"browserify-zlib":{"name":"browserify-zlib","version":"0.2.0","tarball":"https://registry.npmjs.org/browserify-zlib/-/browserify-zlib-0.2.0.tgz","sha1":"2869459d9aa3be245fe8fe2ca1f46e2e7f54d73f","dependencies":["pako"]},"pako":{"name":"pako","version":"1.0.5","tarball":"https://registry.npmjs.org/pako/-/pako-1.0.5.tgz","sha1":"d2205dfe5b9da8af797e7c163db4d1f84e4600bc"},"browserslist":{"name":"browserslist","version":"4.16.6","tarball":"https://registry.npmjs.org/browserslist/-/browserslist-4.16.6.tgz","sha1":"d7901277a5a88e554ed305b183ec9b0c08f66fa2","dependencies":["caniuse-lite","colorette","electron-to-chromium","escalade","node-releases"],"bin":{"browserslist":"cli.js"}},"caniuse-lite":{"name":"caniuse-lite","version":"1.0.30001202","tarball":"https://registry.npmjs.org/caniuse-lite/-/caniuse-lite-1.0.30001202.tgz","sha1":"4cb3bd5e8a808e8cd89e4e66c549989bc8137201"},"buffer":{"name":"buffer","version":"4.3.0","tarball":"https://registry.npmjs.org/buffer/-/buffer-4.3.0.tgz","sha1":"b09b39dbee314233104d7d0cbd6edf928d89e4bd","dependencies":["base64-js","ieee754","isarray"]},"base64-js":{"name":"base64-js","version":"1.0.2","tarball":"https://registry.npmjs.org/base64-js/-/base64-js-1.0.2.tgz","sha1":"474211c95e6cf2a547db461e4f6778b51d08fa65","dependencies":[]},"ieee754":{"name":"ieee754","version":"1.1.4","tarball":"https://registry.npmjs.org/ieee754/-/ieee754-1.1.4.tgz","sha1":"e3ec65200d4ad531d359aabdb6d3ec812699a30b","dependencies":[]},"escape-string-regexp":{"name":"escape-string-regexp","version":"1.0.5","tarball":"https://registry.npmjs.org/escape-string-regexp/-/escape-string-regexp-1.0.5.tgz","sha1":"1b61c0562190a8dff6ae3bb2cf0200ca130b86d4"},"chokidar":{"name":"chokidar","version":"3.5.1","tarball":"https://registry.npmjs.org/chokidar/-/chokidar-3.5.1.tgz","sha1":"ee9ce7bbebd2b79f49f304799d5468e31e14e68a","dependencies":["anymatch","braces","glob-parent","is-binary-path","is-glob","normalize-path","readdirp","fsevents"]},"anymatch":{"name":"anymatch","version":"3.1.1","tarball":"https://registry.npmjs.org/anymatch/-/anymatch-3.1.1.tgz","sha1":"c55ecf02185e2469259399310c173ce31233b142","dependencies":["normalize-path","picomatch"]},"normalize-path":{"name":"normalize-path","version":"3.0.0","tarball":"https://registry.npmjs.org/normalize-path/-/normalize-path-3.0.0.tgz","sha1":"0dcd69ff23a1c9b11fd0978316644a0388216a65"},"braces":{"name":"braces","version":"3.0.2","tarball":"https://registry.npmjs.org/braces/-/braces-3.0.2.tgz","sha1":"3454e1a462ee8d599e236df336cd9ea4f8afe107","dependencies":["fill-range"]},"fill-range":{"name":"fill-range","version":"7.0.1","tarball":"https://registry.npmjs.org/fill-range/-/fill-range-7.0.1.tgz","sha1":"1919a6a7c75fe38b2c7c77e5198535da9acdda40","dependencies":["to-regex-range"]},"to-regex-range":{"name":"to-regex-range","version":"5.0.1","tarball":"https://registry.npmjs.org/to-regex-range/-/to-regex-range-5.0.1.tgz","sha1":"1648c44aae7c8d988a326018ed72f5b4dd0392e4","dependencies":["is-number"]},"is-number":{"name":"is-number","version":"7.0.0","tarball":"https://registry.npmjs.org/is-number/-/is-number-7.0.0.tgz","sha1":"7535345b896734d5f80c4d06c50955527a14f12b"},"glob-parent":{"name":"glob-parent","version":"5.1.0","tarball":"https://registry.npmjs.org/glob-parent/-/glob-parent-5.1.0.tgz","sha1":"5f4c1d1e748d30cd73ad2944b3577a81b081e8c2","dependencies":["is-glob"]},"is-glob":{"name":"is-glob","version":"4.0.1","tarball":"https://registry.npmjs.org/is-glob/-/is-glob-4.0.1.tgz","sha1":"7567dbe9f2f5e2467bc77ab83c4a29482407a5dc","dependencies":["is-extglob"]},"is-extglob":{"name":"is-extglob","version":"2.1.1","tarball":"https://registry.npmjs.org/is-extglob/-/is-extglob-2.1.1.tgz","sha1":"a88c02535791f02ed37c76a1b9ea9773c833f8c2"},"is-binary-path":{"name":"is-binary-path","version":"2.1.0","tarball":"https://registry.npmjs.org/is-binary-path/-/is-binary-path-2.1.0.tgz","sha1":"ea1f7f3b80f064236e83470f86c09c254fb45b09","dependencies":["binary-extensions"]},"binary-extensions":{"name":"binary-extensions","version":"2.0.0","tarball":"https://registry.npmjs.org/binary-extensions/-/binary-extensions-2.0.0.tgz","sha1":"23c0df14f6a88077f5f986c0d167ec03c3d5537c"},"constants-browserify":{"name":"constants-browserify","version":"1.0.0","tarball":"https://registry.npmjs.org/constants-browserify/-/constants-browserify-1.0.0.tgz","sha1":"c20b96d8c617748aaf1c16021760cd27fcb8cb75","dependencies":[]},"crypto-browserify":{"name":"crypto-browserify","version":"3.11.0","tarball":"https://registry.npmjs.org/crypto-browserify/-/crypto-browserify-3.11.0.tgz","sha1":"3652a0906ab9b2a7e0c3ce66a408e957a2485522","dependencies":["browserify-cipher","browserify-sign","create-ecdh","create-hash","create-hmac","diffie-hellman","inherits","pbkdf2","public-encrypt","randombytes"]},"browserify-cipher":{"name":"browserify-cipher","version":"1.0.0","tarball":"https://registry.npmjs.org/browserify-cipher/-/browserify-cipher-1.0.0.tgz","sha1":"9988244874bf5ed4e28da95666dcd66ac8fc363a","dependencies":["browserify-aes","browserify-des","evp_bytestokey"]},"browserify-aes":{"name":"browserify-aes","version":"1.0.4","tarball":"https://registry.npmjs.org/browserify-aes/-/browserify-aes-1.0.4.tgz","sha1":"f233838d6f1759599960c0a19e85ca1630f4bb6e","dependencies":["buffer-xor","create-hash","inherits"]},"buffer-xor":{"name":"buffer-xor","version":"1.0.2","tarball":"https://registry.npmjs.org/buffer-xor/-/buffer-xor-1.0.2.tgz","sha1":"231e44571f644bde0789026f61de6e923167124a"},"browserify-des":{"name":"browserify-des","version":"1.0.0","tarball":"https://registry.npmjs.org/browserify-des/-/browserify-des-1.0.0.tgz","sha1":"daa277717470922ed2fe18594118a175439721dd","dependencies":["cipher-base","des.js","inherits"]},"cipher-base":{"name":"cipher-base","version":"1.0.1","tarball":"https://registry.npmjs.org/cipher-base/-/cipher-base-1.0.1.tgz","sha1":"b714888e810519106b3b039948e4fc9e2718c563","dependencies":["inherits"]},"inherits":{"name":"inherits","version":"2.0.3","tarball":"https://registry.npmjs.org/inherits/-/inherits-2.0.3.tgz","sha1":"633c2c83e3da42a502f52466022480f4208261de"},"des.js":{"name":"des.js","version":"1.0.0","tarball":"https://registry.npmjs.org/des.js/-/des.js-1.0.0.tgz","sha1":"c074d2e2aa6a8a9a07dbd61f9a15c2cd83ec8ecc","dependencies":["inherits","minimalistic-assert"]},"evp_bytestokey":{"name":"evp_bytestokey","version":"1.0.0","tarball":"https://registry.npmjs.org/evp_bytestokey/-/evp_bytestokey-1.0.0.tgz","sha1":"497b66ad9fef65cd7c08a6180824ba1476b66e53","dependencies":["create-hash"]},"create-hash":{"name":"create-hash","version":"1.1.0","tarball":"https://registry.npmjs.org/create-hash/-/create-hash-1.1.0.tgz","sha1":"c2ab96b5d4ece5f22df2ef4306803d14da6931e7","dependencies":["inherits","ripemd160","sha.js"]},"browserify-sign":{"name":"browserify-sign","version":"4.0.0","tarball":"https://registry.npmjs.org/browserify-sign/-/browserify-sign-4.0.0.tgz","sha1":"10773910c3c206d5420a46aad8694f820b85968f","dependencies":["bn.js","browserify-rsa","create-hash","create-hmac","elliptic","inherits","parse-asn1"]},"bn.js":{"name":"bn.js","version":"4.1.0","tarball":"https://registry.npmjs.org/bn.js/-/bn.js-4.1.0.tgz","sha1":"35105abe0809c082007744650b8234b2f9c9ada3"},"create-ecdh":{"name":"create-ecdh","version":"4.0.0","tarball":"https://registry.npmjs.org/create-ecdh/-/create-ecdh-4.0.0.tgz","sha1":"888c723596cdf7612f6498233eebd7a35301737d","dependencies":["bn.js","elliptic"]},"create-hmac":{"name":"create-hmac","version":"1.1.0","tarball":"https://registry.npmjs.org/create-hmac/-/create-hmac-1.1.0.tgz","sha1":"92f8b6378471f4bc67eefc9dee6622df6b8754be","dependencies":["create-hash","inherits"]},"diffie-hellman":{"name":"diffie-hellman","version":"5.0.0","tarball":"https://registry.npmjs.org/diffie-hellman/-/diffie-hellman-5.0.0.tgz","sha1":"f3c957cfd5419fea048540b39a751d7e4363f031","dependencies":["bn.js","miller-rabin","randombytes"]},"cssnano-simple":{"name":"cssnano-simple","version":"2.0.0","tarball":"https://registry.npmjs.org/cssnano-simple/-/cssnano-simple-2.0.0.tgz","sha1":"930d9dcd8ba105c5a62ce719cb00854da58b5c05","dependencies":["cssnano-preset-simple"]},"cssnano-preset-simple":{"name":"cssnano-preset-simple","version":"2.0.0","tarball":"https://registry.npmjs.org/cssnano-preset-simple/-/cssnano-preset-simple-2.0.0.tgz","sha1":"b55e72cb970713f425560a0e141b0335249e2f96","dependencies":["caniuse-lite"]},"domain-browser":{"name":"domain-browser","version":"1.1.1","tarball":"https://registry.npmjs.org/domain-browser/-/domain-browser-1.1.1.tgz","sha1":"0123c1b9afe3bb7c8a9e856177b2059440957de0"},"encoding":{"name":"encoding","version":"0.1.13","tarball":"https://registry.npmjs.org/encoding/-/encoding-0.1.13.tgz","sha1":"56574afdd791f54a8e9b2785c0582a2d26210fa9","dependencies":["iconv-lite"]},"iconv-lite":{"name":"iconv-lite","version":"0.6.2","tarball":"https://registry.npmjs.org/iconv-lite/-/iconv-lite-0.6.2.tgz","sha1":"ce13d1875b0c3a674bd6a04b7f76b01b1b6ded01","dependencies":["safer-buffer"]},"safer-buffer":{"name":"safer-buffer","version":">= 2.1.2 < 3.0.0"},"etag":{"name":"etag","version":"1.8.1","tarball":"https://registry.npmjs.org/etag/-/etag-1.8.1.tgz","sha1":"41ae2eeb65efa62268aebfea83ac7d79299b0887","dependencies":[]},"find-cache-dir":{"name":"find-cache-dir","version":"3.3.1","tarball":"https://registry.npmjs.org/find-cache-dir/-/find-cache-dir-3.3.1.tgz","sha1":"89b33fad4a4670daa94f855f7fbe31d6d84fe880","dependencies":["commondir","make-dir","pkg-dir"]},"commondir":{"name":"commondir","version":"1.0.1","tarball":"https://registry.npmjs.org/commondir/-/commondir-1.0.1.tgz","sha1":"ddd800da0c66127393cca5950ea968a3aaf1253b","dependencies":[]},"make-dir":{"name":"make-dir","version":"3.0.2","tarball":"https://registry.npmjs.org/make-dir/-/make-dir-3.0.2.tgz","sha1":"04a1acbf22221e1d6ef43559f43e05a90dbb4392","dependencies":["semver"]},"semver":{"name":"semver","version":"6.0.0","tarball":"https://registry.npmjs.org/semver/-/semver-6.0.0.tgz","sha1":"05e359ee571e5ad7ed641a6eec1e547ba52dea65"},"pkg-dir":{"name":"pkg-dir","version":"4.1.0","tarball":"https://registry.npmjs.org/pkg-dir/-/pkg-dir-4.1.0.tgz","sha1":"aaeb91c0d3b9c4f74a44ad849f4de34781ae01de","dependencies":["find-up"]},"find-up":{"name":"find-up","version":"3.0.0","tarball":"https://registry.npmjs.org/find-up/-/find-up-3.0.0.tgz","sha1":"49169f1d7993430646da61ecc5ae355c21c97b73","dependencies":["locate-path"]},"locate-path":{"name":"locate-path","version":"3.0.0","tarball":"https://registry.npmjs.org/locate-path/-/locate-path-3.0.0.tgz","sha1":"dbec3b3ab759758071b58fe59fc41871af21400e","dependencies":["p-locate","path-exists"]},"p-locate":{"name":"p-locate","version":"3.0.0","tarball":"https://registry.npmjs.org/p-locate/-/p-locate-3.0.0.tgz","sha1":"322d69a05c0264b25997d9f40cd8a891ab0064a4","dependencies":["p-limit"]},"p-limit":{"name":"p-limit","version":"3.1.0","tarball":"https://registry.npmjs.org/p-limit/-/p-limit-3.1.0.tgz","sha1":"e1daccbe78d0d1388ca18c64fea38e3e57e3706b","dependencies":["yocto-queue"]},"p-try":{"name":"p-try","version":"2.0.0","tarball":"https://registry.npmjs.org/p-try/-/p-try-2.0.0.tgz","sha1":"85080bb87c64688fa47996fe8f7dfbe8211760b1"},"path-exists":{"name":"path-exists","version":"3.0.0","tarball":"https://registry.npmjs.org/path-exists/-/path-exists-3.0.0.tgz","sha1":"ce0ebeaa5f78cb18925ea7d810d7b59b010fd515"},"get-orientation":{"name":"get-orientation","version":"1.1.2","tarball":"https://registry.npmjs.org/get-orientation/-/get-orientation-1.1.2.tgz","sha1":"20507928951814f8a91ded0a0e67b29dfab98947","dependencies":["stream-parser"]},"stream-parser":{"name":"stream-parser","version":"0.3.1","tarball":"https://registry.npmjs.org/stream-parser/-/stream-parser-0.3.1.tgz","sha1":"1618548694420021a1182ff0af1911c129761773","dependencies":["debug"]},"debug":{"name":"debug","version":"2"},"https-browserify":{"name":"https-browserify","version":"1.0.0","tarball":"https://registry.npmjs.org/https-browserify/-/https-browserify-1.0.0.tgz","sha1":"ec06c10e0a34c0f2faf199f7fd7fc78fffd03c73","dependencies":[]},"jest-worker":{"name":"jest-worker","version":"27.0.0-next.5","tarball":"https://registry.npmjs.org/jest-worker/-/jest-worker-27.0.0-next.5.tgz","sha1":"5985ee29b12a4e191f4aae4bb73b97971d86ec28","dependencies":["@types/node","merge-stream","supports-color"]},"@types/node":{"name":"@types/node","version":"15.3.1","tarball":"https://registry.npmjs.org/@types/node/-/node-15.3.1.tgz","sha1":"23a06b87eedb524016616e886b116b8fdcb180af","dependencies":[]},"merge-stream":{"name":"merge-stream","version":"2.0.0","tarball":"https://registry.npmjs.org/merge-stream/-/merge-stream-2.0.0.tgz","sha1":"52823629a14dd00c9770fb6ad47dc6310f2c1f60","dependencies":[]},"native-url":{"name":"native-url","version":"0.3.4","tarball":"https://registry.npmjs.org/native-url/-/native-url-0.3.4.tgz","sha1":"29c943172aed86c63cee62c8c04db7f5756661f8","dependencies":["querystring"]},"querystring":{"name":"querystring","version":"0.2.0","tarball":"https://registry.npmjs.org/querystring/-/querystring-0.2.0.tgz","sha1":"b209849203bb25df820da756e747005878521620"},"node-fetch":{"name":"node-fetch","version":"2.6.1","tarball":"https://registry.npmjs.org/node-fetch/-/node-fetch-2.6.1.tgz","sha1":"045bd323631f76ed2e2b55573394416b639a0052","dependencies":[]},"node-html-parser":{"name":"node-html-parser","version":"1.4.9","tarball":"https://registry.npmjs.org/node-html-parser/-/node-html-parser-1.4.9.tgz","sha1":"3c8f6cac46479fae5800725edb532e9ae8fd816c","dependencies":["he"]},"he":{"name":"he","version":"1.2.0","tarball":"https://registry.npmjs.org/he/-/he-1.2.0.tgz","sha1":"84ae65fa7eafb165fddb61566ae14baf05664f0f"},"node-libs-browser":{"name":"node-libs-browser","version":"2.2.1","tarball":"https://registry.npmjs.org/node-libs-browser/-/node-libs-browser-2.2.1.tgz","sha1":"b64f513d18338625f90346d27b0d235e631f6425","dependencies":["assert","browserify-zlib","buffer","console-browserify","constants-browserify","crypto-browserify","domain-browser","events","https-browserify","os-browserify","path-browserify","process","punycode","querystring-es3","readable-stream","stream-browserify","stream-http","string_decoder","timers-browserify","tty-browserify","url","util","vm-browserify"]},"util":{"name":"util","version":"0.12.3","tarball":"https://registry.npmjs.org/util/-/util-0.12.3.tgz","sha1":"971bb0292d2cc0c892dab7c6a5d37c2bec707888","dependencies":["inherits","is-arguments","is-generator-function","is-typed-array","safe-buffer","which-typed-array"]},"isarray":{"name":"isarray","version":"1.0.0","tarball":"https://registry.npmjs.org/isarray/-/isarray-1.0.0.tgz","sha1":"bb935d48582cba168c06834957a54a3e07124f11","dependencies":[]},"console-browserify":{"name":"console-browserify","version":"1.1.0","tarball":"https://registry.npmjs.org/console-browserify/-/console-browserify-1.1.0.tgz","sha1":"f0241c45730a9fc6323b206dbf38edc741d0bb10","dependencies":["date-now"]},"date-now":{"name":"date-now","version":"0.1.4","tarball":"https://registry.npmjs.org/date-now/-/date-now-0.1.4.tgz","sha1":"eaf439fd4d4848ad74e5cc7dbef200672b9e345b","dependencies":[]},"os-browserify":{"name":"os-browserify","version":"0.3.0","tarball":"https://registry.npmjs.org/os-browserify/-/os-browserify-0.3.0.tgz","sha1":"854373c7f5c2315914fc9bfc6bd8238fdda1ec27","dependencies":[]},"yocto-queue":{"name":"yocto-queue","version":"0.1.0","tarball":"https://registry.npmjs.org/yocto-queue/-/yocto-queue-0.1.0.tgz","sha1":"0294eb3dee05028d31ee1a5fa2c556a6aaf10a1b"},"path-browserify":{"name":"path-browserify","version":"1.0.1","tarball":"https://registry.npmjs.org/path-browserify/-/path-browserify-1.0.1.tgz","sha1":"d98454a9c3753d5790860f16f68867b9e46be1fd","dependencies":[]},"pnp-webpack-plugin":{"name":"pnp-webpack-plugin","version":"1.6.4","tarball":"https://registry.npmjs.org/pnp-webpack-plugin/-/pnp-webpack-plugin-1.6.4.tgz","sha1":"c9711ac4dc48a685dabafc86f8b6dd9f8df84149","dependencies":["ts-pnp"]},"ts-pnp":{"name":"ts-pnp","version":"1.1.6","tarball":"https://registry.npmjs.org/ts-pnp/-/ts-pnp-1.1.6.tgz","sha1":"389a24396d425a0d3162e96d2b4638900fdc289a"},"postcss":{"name":"postcss","version":"8.2.13","tarball":"https://registry.npmjs.org/postcss/-/postcss-8.2.13.tgz","sha1":"dbe043e26e3c068e45113b1ed6375d2d37e2129f","dependencies":["colorette","nanoid","source-map"]},"colorette":{"name":"colorette","version":"1.2.2","tarball":"https://registry.npmjs.org/colorette/-/colorette-1.2.2.tgz","sha1":"cbcc79d5e99caea2dbf10eb3a26fd8b3e6acfa94"},"process":{"name":"process","version":"0.11.10","tarball":"https://registry.npmjs.org/process/-/process-0.11.10.tgz","sha1":"7332300e840161bda3e69a1d1d91a7d4bc16f182","dependencies":[]},"prop-types":{"name":"prop-types","version":"15.7.2","tarball":"https://registry.npmjs.org/prop-types/-/prop-types-15.7.2.tgz","sha1":"52c41e75b8c87e72b9d9360e0206b99dcbffa6c5","dependencies":["loose-envify","object-assign","react-is"]},"loose-envify":{"name":"loose-envify","version":"1.4.0","tarball":"https://registry.npmjs.org/loose-envify/-/loose-envify-1.4.0.tgz","sha1":"71ee51fa7be4caec1a63839f7e682d8132d30caf","dependencies":["js-tokens"],"bin":{"loose-envify":"cli.js"}},"js-tokens":{"name":"js-tokens","version":"3.0.0 || 4.0.0"},"object-assign":{"name":"object-assign","version":"4.1.1","tarball":"https://registry.npmjs.org/object-assign/-/object-assign-4.1.1.tgz","sha1":"2109adc7965887cfc05cbbd442cac8bfbb360863"},"querystring-es3":{"name":"querystring-es3","version":"0.2.1","tarball":"https://registry.npmjs.org/querystring-es3/-/querystring-es3-0.2.1.tgz","sha1":"9ec61f79049875707d69414596fd907a4d711e73","dependencies":[]},"raw-body":{"name":"raw-body","version":"2.4.1","tarball":"https://registry.npmjs.org/raw-body/-/raw-body-2.4.1.tgz","sha1":"30ac82f98bb5ae8c152e67149dac8d55153b168c","dependencies":["bytes","http-errors","iconv-lite","unpipe"]},"bytes":{"name":"bytes","version":"3.1.0","tarball":"https://registry.npmjs.org/bytes/-/bytes-3.1.0.tgz","sha1":"f6cf7933a360e0588fa9fde85651cdc7f805d1f6"},"react-is":{"name":"react-is","version":"16.13.1","tarball":"https://registry.npmjs.org/react-is/-/react-is-16.13.1.tgz","sha1":"789729a4dc36de2999dc156dd6c1d9c18cea56a4","dependencies":[]},"react-refresh":{"name":"react-refresh","version":"0.8.3","tarball":"https://registry.npmjs.org/react-refresh/-/react-refresh-0.8.3.tgz","sha1":"721d4657672d400c5e3c75d063c4a85fb2d5d68f","dependencies":[]},"stream-browserify":{"name":"stream-browserify","version":"3.0.0","tarball":"https://registry.npmjs.org/stream-browserify/-/stream-browserify-3.0.0.tgz","sha1":"22b0a2850cdf6503e73085da1fc7b7d0c2122f2f","dependencies":["inherits","readable-stream"]},"stream-http":{"name":"stream-http","version":"3.1.1","tarball":"https://registry.npmjs.org/stream-http/-/stream-http-3.1.1.tgz","sha1":"0370a8017cf8d050b9a8554afe608f043eaff564","dependencies":["builtin-status-codes","inherits","readable-stream","xtend"]},"builtin-status-codes":{"name":"builtin-status-codes","version":"3.0.0","tarball":"https://registry.npmjs.org/builtin-status-codes/-/builtin-status-codes-3.0.0.tgz","sha1":"85982878e21b98e1c66425e03d0174788f569ee8"},"string_decoder":{"name":"string_decoder","version":"1.3.0","tarball":"https://registry.npmjs.org/string_decoder/-/string_decoder-1.3.0.tgz","sha1":"42f114594a46cf1a8e30b0a84f56c78c3edac21e","dependencies":["safe-buffer"]},"safe-buffer":{"name":"safe-buffer","version":"5.1.1","tarball":"https://registry.npmjs.org/safe-buffer/-/safe-buffer-5.1.1.tgz","sha1":"893312af69b2123def71f57889001671eeb2c853"},"styled-jsx":{"name":"styled-jsx","version":"3.3.2","tarball":"https://registry.npmjs.org/styled-jsx/-/styled-jsx-3.3.2.tgz","sha1":"2474601a26670a6049fb4d3f94bd91695b3ce018","dependencies":["@babel/types","babel-plugin-syntax-jsx","convert-source-map","loader-utils","source-map","string-hash","stylis","stylis-rule-sheet"]},"@babel/types":{"name":"@babel/types","version":"7.8.3","tarball":"https://registry.npmjs.org/@babel/types/-/types-7.8.3.tgz","sha1":"5a383dffa5416db1b73dedffd311ffd0788fb31c","dependencies":["esutils","lodash","to-fast-properties"]},"esutils":{"name":"esutils","version":"2.0.2","tarball":"https://registry.npmjs.org/esutils/-/esutils-2.0.2.tgz","sha1":"0abf4f1caa5bcb1f7a9d8acc6dea4faaa04bac9b"},"babel-plugin-syntax-jsx":{"name":"babel-plugin-syntax-jsx","version":"6.18.0","tarball":"https://registry.npmjs.org/babel-plugin-syntax-jsx/-/babel-plugin-syntax-jsx-6.18.0.tgz","sha1":"0af32a9a6e13ca7a3fd5069e62d7b0f58d0d8946","dependencies":[]},"convert-source-map":{"name":"convert-source-map","version":"1.7.0","tarball":"https://registry.npmjs.org/convert-source-map/-/convert-source-map-1.7.0.tgz","sha1":"17a2cb882d7f77d3490585e2ce6c524424a3a442","dependencies":["safe-buffer"]},"loader-utils":{"name":"loader-utils","version":"1.2.3","tarball":"https://registry.npmjs.org/loader-utils/-/loader-utils-1.2.3.tgz","sha1":"1ff5dc6911c9f0a062531a4c04b609406108c2c7","dependencies":["big.js","emojis-list","json5"]},"big.js":{"name":"big.js","version":"5.2.2","tarball":"https://registry.npmjs.org/big.js/-/big.js-5.2.2.tgz","sha1":"65f0af382f578bcdc742bd9c281e9cb2d7768328"},"source-map":{"name":"source-map","version":"0.7.3","tarball":"https://registry.npmjs.org/source-map/-/source-map-0.7.3.tgz","sha1":"5302f8169031735226544092e64981f751750383"},"timers-browserify":{"name":"timers-browserify","version":"2.0.12","tarball":"https://registry.npmjs.org/timers-browserify/-/timers-browserify-2.0.12.tgz","sha1":"44a45c11fbf407f34f97bccd1577c652361b00ee","dependencies":["setimmediate"]},"setimmediate":{"name":"setimmediate","version":"1.0.4","tarball":"https://registry.npmjs.org/setimmediate/-/setimmediate-1.0.4.tgz","sha1":"20e81de622d4a02588ce0c8da8973cbcf1d3138f"},"tty-browserify":{"name":"tty-browserify","version":"0.0.1","tarball":"https://registry.npmjs.org/tty-browserify/-/tty-browserify-0.0.1.tgz","sha1":"3f05251ee17904dfd0677546670db9651682b811","dependencies":[]},"use-subscription":{"name":"use-subscription","version":"1.5.1","tarball":"https://registry.npmjs.org/use-subscription/-/use-subscription-1.5.1.tgz","sha1":"73501107f02fad84c6dd57965beb0b75c68c42d1","dependencies":["object-assign"]},"vm-browserify":{"name":"vm-browserify","version":"1.1.2","tarball":"https://registry.npmjs.org/vm-browserify/-/vm-browserify-1.1.2.tgz","sha1":"78641c488b8e6ca91a75f511e7a3b32a86e5dda0","dependencies":[]},"watchpack":{"name":"watchpack","version":"2.1.1","tarball":"https://registry.npmjs.org/watchpack/-/watchpack-2.1.1.tgz","sha1":"e99630550fca07df9f90a06056987baa40a689c7","dependencies":["glob-to-regexp","graceful-fs"]},"glob-to-regexp":{"name":"glob-to-regexp","version":"0.4.1","tarball":"https://registry.npmjs.org/glob-to-regexp/-/glob-to-regexp-0.4.1.tgz","sha1":"c75297087c851b9a578bd217dd59a92f59fe546e"}}}}